<?xml version="1.0" encoding="UTF-8"?><record_update table="sys_rte_eb_field_mapping">
    <sys_rte_eb_field_mapping action="DELETE">
        <order>100</order>
        <referenced_sys_rte_eb_entity display_value="Physical connection 1">2ecf1bfb1b4cc210da698666624bcb9e</referenced_sys_rte_eb_entity>
        <source_sys_rte_eb_field/>
        <sys_class_name>sys_rte_eb_field_mapping</sys_class_name>
        <sys_created_by>alex.frankel@exfo.com</sys_created_by>
        <sys_created_on>2024-02-06 12:27:33</sys_created_on>
        <sys_id>1ae06b7f1b4cc210da698666624bcb51</sys_id>
        <sys_mod_count>0</sys_mod_count>
        <sys_name/>
        <sys_package display_value="Service Graph Connector for EXFO" source="x_snc_exfo_cmdb">aa514eec877274103e867518cebb35ae</sys_package>
        <sys_policy/>
        <sys_rte_eb_definition display_value="">24b681d887600950c4a3c99d0ebb3502</sys_rte_eb_definition>
        <sys_rte_eb_entity_mapping display_value="tempToTNI CI Attributes 1">3cd0e77f1b4cc210da698666624bcb8d</sys_rte_eb_entity_mapping>
        <sys_scope display_value="Service Graph Connector for EXFO">aa514eec877274103e867518cebb35ae</sys_scope>
        <sys_update_name>sys_rte_eb_field_mapping_1ae06b7f1b4cc210da698666624bcb51</sys_update_name>
        <sys_updated_by>alex.frankel@exfo.com</sys_updated_by>
        <sys_updated_on>2024-02-06 12:27:33</sys_updated_on>
        <target_sys_rte_eb_field/>
    </sys_rte_eb_field_mapping>
    <sys_update_version action="INSERT_OR_UPDATE">
        <action>DELETE</action>
        <application display_value="Service Graph Connector for EXFO">aa514eec877274103e867518cebb35ae</application>
        <file_path/>
        <instance_id>d8108846db93a190ebdd2a5913961934</instance_id>
        <instance_name>ven06184</instance_name>
        <name>sys_rte_eb_field_mapping_1ae06b7f1b4cc210da698666624bcb51</name>
        <payload><![CDATA[<?xml version="1.0" encoding="UTF-8"?><record_update table="sys_rte_eb_field_mapping"><sys_rte_eb_field_mapping action="INSERT_OR_UPDATE"><order>100</order><referenced_sys_rte_eb_entity display_value="Physical connection 1">2ecf1bfb1b4cc210da698666624bcb9e</referenced_sys_rte_eb_entity><source_sys_rte_eb_field/><sys_class_name>sys_rte_eb_field_mapping</sys_class_name><sys_created_by>alex.frankel@exfo.com</sys_created_by><sys_created_on>2024-02-06 12:27:33</sys_created_on><sys_id>1ae06b7f1b4cc210da698666624bcb51</sys_id><sys_mod_count>0</sys_mod_count><sys_name/><sys_package display_value="Service Graph Connector for EXFO" source="x_snc_exfo_cmdb">aa514eec877274103e867518cebb35ae</sys_package><sys_policy/><sys_rte_eb_definition display_value="">24b681d887600950c4a3c99d0ebb3502</sys_rte_eb_definition><sys_rte_eb_entity_mapping display_value="tempToTNI CI Attributes 1">3cd0e77f1b4cc210da698666624bcb8d</sys_rte_eb_entity_mapping><sys_scope display_value="Service Graph Connector for EXFO">aa514eec877274103e867518cebb35ae</sys_scope><sys_update_name>sys_rte_eb_field_mapping_1ae06b7f1b4cc210da698666624bcb51</sys_update_name><sys_updated_by>alex.frankel@exfo.com</sys_updated_by><sys_updated_on>2024-02-06 12:27:33</sys_updated_on><target_sys_rte_eb_field/></sys_rte_eb_field_mapping></record_update>]]></payload>
        <payload_hash>1274524426</payload_hash>
        <record_name/>
        <reverted_from/>
        <source>3c8da93d1b9c8e10da698666624bcb2a</source>
        <source_table>sys_update_set</source_table>
        <state>previous</state>
        <sys_created_by>alex.frankel@exfo.com</sys_created_by>
        <sys_created_on>2024-03-08 16:44:51</sys_created_on>
        <sys_id>2115084e1b70c6106e86e0cb234bcb53</sys_id>
        <sys_mod_count>0</sys_mod_count>
        <sys_recorded_at>18e1ef3fff80000001</sys_recorded_at>
        <sys_updated_by>alex.frankel@exfo.com</sys_updated_by>
        <sys_updated_on>2024-03-08 16:44:51</sys_updated_on>
        <type>RTE Field Mapping</type>
        <update_guid>e915084e8b70c61081858b82eb86ba52</update_guid>
        <update_guid_history>e915084e8b70c61081858b82eb86ba52:0,af646b3cf3d48a1013d63c52be45547a:0,4d8153acb7d40a10bd7cf1fdc4329396:-1090202384,ecd61968f314c6109e0cb62985936e98:0,47b419a88dd0c610691b60d9d1958de1:693519658,2ee06b7f504cc210f377ab0eacae4f52:-295507214</update_guid_history>
    </sys_update_version>
    <sys_metadata_delete action="INSERT_OR_UPDATE">
        <sys_audit_delete/>
        <sys_class_name>sys_metadata_delete</sys_class_name>
        <sys_created_by>alex.frankel@exfo.com</sys_created_by>
        <sys_created_on>2024-03-08 16:45:05</sys_created_on>
        <sys_db_object display_value="" name="sys_rte_eb_field_mapping">sys_rte_eb_field_mapping</sys_db_object>
        <sys_id>2baed3d4279b42f5981d33606dde9bb9</sys_id>
        <sys_metadata>1ae06b7f1b4cc210da698666624bcb51</sys_metadata>
        <sys_mod_count>0</sys_mod_count>
        <sys_name/>
        <sys_package display_value="Service Graph Connector for EXFO" source="x_snc_exfo_cmdb">aa514eec877274103e867518cebb35ae</sys_package>
        <sys_parent/>
        <sys_policy/>
        <sys_scope display_value="Service Graph Connector for EXFO">aa514eec877274103e867518cebb35ae</sys_scope>
        <sys_scope_delete display_value="">0146885dac0341b58009a97623912db9</sys_scope_delete>
        <sys_update_name>sys_rte_eb_field_mapping_1ae06b7f1b4cc210da698666624bcb51</sys_update_name>
        <sys_update_version display_value="sys_rte_eb_field_mapping_1ae06b7f1b4cc210da698666624bcb51">2115084e1b70c6106e86e0cb234bcb53</sys_update_version>
        <sys_updated_by>alex.frankel@exfo.com</sys_updated_by>
        <sys_updated_on>2024-03-08 16:45:05</sys_updated_on>
    </sys_metadata_delete>
</record_update>
